adrenaline/__init__.py
adrenaline/__main__.py
adrenaline/errors.py
adrenaline/impl_registry.py
adrenaline/types.py
adrenaline/version.py
adrenaline/_impl/__init__.py
adrenaline/_impl/darwin.py
adrenaline/_impl/dummy.py
adrenaline/_impl/failing.py
adrenaline/_impl/linux.py
adrenaline/_impl/windows.py
adrenaline-4.0.1.dist-info/METADATA
adrenaline-4.0.1.dist-info/WHEEL
adrenaline-4.0.1.dist-info/entry_points.txt
adrenaline-4.0.1.dist-info/RECORD
