Metadata-Version: 2.4
Name: adrenaline
Version: 4.0.1
Summary: Keep your OS from sleeping (supports Windows and macOS)
Project-URL: Homepage, https://github.com/ntamas/adrenaline
Project-URL: Repository, https://github.com/ntamas/adrenaline
Author-email: Tamas Nepusz <ntamas@gmail.com>
License-Expression: MIT
Requires-Python: >=3.9
Requires-Dist: jeepney>=0.8.0; sys_platform == 'linux'
Requires-Dist: pyobjc-core>=11.0; sys_platform == 'darwin'
Requires-Dist: pyobjc-framework-cocoa>=11.0; sys_platform == 'darwin'
